palettify-0.0.6.dist-info/METADATA
palettify-0.0.6.dist-info/WHEEL
palettify-0.0.6.dist-info/top_level.txt
palettify-0.0.6.dist-info/LICENSE
palettify-0.0.6.dist-info/entry_points.txt
palettify-0.0.6.dist-info/RECORD
palettify/__main__.py
palettify/palettify.py
palettify/cli.py
palettify/_about.py
palettify/__init__.py
palettify/internal/convert.cpython-39-x86_64-linux-gnu.so
palettify/internal/convert.c
palettify/internal/scale.py
palettify/internal/convert.pyx
palettify/internal/loader.py
palettify/internal/__init__.py
